prelm
